<?xml version="1.0"?>
<!DOCTYPE hibernate-mapping PUBLIC "-//Hibernate/Hibernate Mapping DTD 3.0//EN"
"http://www.hibernate.org/dtd/hibernate-mapping-3.0.dtd">
<!-- Generated 15-ene-2017 23:16:30 by Hibernate Tools 4.3.1.Final -->
<hibernate-mapping>
    <class name="ejerciciospropuestos_4_4_1.Series" table="series" schema="public" optimistic-lock="version">
        <id name="codigo" type="int">
            <column name="codigo" />
            <generator class="assigned" />
        </id>
        <property name="nombre" type="string">
            <column name="nombre" length="60" />
        </property>
        <property name="cadena" type="string">
            <column name="cadena" length="35" />
        </property>
        <property name="duracion" type="java.lang.Integer">
            <column name="duracion" />
        </property>
    </class>
</hibernate-mapping>
